{"errors":[],"warnings":[],"namedChunkGroups":{"polyfill":{"chunks":[0,4],"assets":["webpack-runtime-46a731aedd81f279b11c.js","webpack-runtime-46a731aedd81f279b11c.js.map","polyfill-0eb32b4237d999938e14.js","polyfill-0eb32b4237d999938e14.js.map"],"children":{},"childAssets":{}},"app":{"chunks":[0,3,1],"assets":["webpack-runtime-46a731aedd81f279b11c.js","webpack-runtime-46a731aedd81f279b11c.js.map","framework-05e34eb4b3d8578f0642.js","framework-05e34eb4b3d8578f0642.js.map","app-1742f1fc18fa5bd13938.js","app-1742f1fc18fa5bd13938.js.map"],"children":{},"childAssets":{}},"component---src-pages-index-tsx":{"chunks":[5,2],"assets":["styles.c0227ea8c69044b9299a.css","styles-29163f9dced6fe4a408a.js","styles-29163f9dced6fe4a408a.js.map","component---src-pages-index-tsx-259fc93ed3589639a759.js","component---src-pages-index-tsx-259fc93ed3589639a759.js.map"],"children":{},"childAssets":{}}},"assetsByChunkName":{"polyfill":["webpack-runtime-46a731aedd81f279b11c.js","polyfill-0eb32b4237d999938e14.js"],"app":["webpack-runtime-46a731aedd81f279b11c.js","framework-05e34eb4b3d8578f0642.js","app-1742f1fc18fa5bd13938.js"],"component---src-pages-index-tsx":["styles.c0227ea8c69044b9299a.css","styles-29163f9dced6fe4a408a.js","component---src-pages-index-tsx-259fc93ed3589639a759.js"]}}